{
  "data": [
    {
      "name": "Gimy(规则)",
      "pic": "https://pkj99.github.io/demo/images/gimy.png",
      "type": "webPlug",
      "ads": "",
      "webUrl": "https://gimy.video/",
      "webOpen": false,
      "click": true,
      "webPlus": {
        "search_url": "https://gimy.video/search/-------------.html?wd={kw}",
        "nav_url": "https:///gimy.video/genre/navCate---navPage.html",
        "web_name": "Gimy",
        "search": true,
        "navHtml": {
          "name": [
            "電影",
            "電視劇",
            "綜藝",
            "動漫",
            "台劇",
            "韓劇",
            "陸劇",
            "美劇",
            "日劇",
            "紀錄片"
          ],
          "cate": [
            "1",
            "2",
            "29",
            "24",
            "14",
            "20",
            "13",
            "16",
            "15",
            "22"
          ],
          "page": "1"
        },
        "html": {
          "episodes": {
            "hasUrlPrefix": false,
            "isListItemAttr": true,
            "listCss": "div.myui-panel_bd.clearfix",
            "isMultiList": true,
            "listCssMulti": "ul > li",
            "listItemAttr": "href",
            "listItemCss": "a",
            "listItemIndex": 0,
            "mainCss": "div.col-md-wide-7.col-xs-1.padding-0",
            "mainIndex": 0
          },
          "nav": {
            "descAttr": "",
            "descCss": "span.pic-text.text-right",
            "descIndex": 0,
            "hasUrlPrefix": false,
            "imgAttr": "data-original",
            "imgCss": "a",
            "imgIndex": 0,
            "isDescAttr": false,
            "isImgAttr": true,
            "isNameAttr": true,
            "isUrlAttr": true,
            "mainCss": "div.myui-content__thumb",
            "mainListIndex": 0,
            "nameAttr": "title",
            "nameCss": "a",
            "nameIndex": 0,
            "searchListCss": "li",
            "urlAttr": "href",
            "urlCss": "a",
            "urlIndex": 0
          },
          "search": {
            "descAttr": "",
            "descCss": "span.pic-text.text-right",
            "descIndex": 0,
            "hasUrlPrefix": false,
            "imgAttr": "data-original",
            "imgCss": "a",
            "imgIndex": 0,
            "isDescAttr": false,
            "isImgAttr": true,
            "isNameAttr": true,
            "isUrlAttr": true,
            "mainCss": "div.myui-panel_bd.col-pd.clearfix",
            "mainListIndex": 0,
            "nameAttr": "title",
            "nameCss": "a",
            "nameIndex": 0,
            "searchListCss": "ul > li",
            "urlAttr": "href",
            "urlCss": "a",
            "urlIndex": 0
          }
        }
      }
    },
    {
      "name": "唐人街(规则)",
      "pic": "https://pkj99.github.io/demo/images/trj.png",
      "type": "webPlug",
      "ads": "",
      "webUrl": "https://www.tangrenjie.tv/",
      "webOpen": false,
      "click": true,
      "webPlus": {
        "search_url": "https://www.tangrenjie.tv/vod/search.html?wd={kw}",
        "nav_url": "https://www.tangrenjie.tv/vod/show/id/navCate/page/navPage.html",
        "web_name": "唐人街",
        "search": true,
        "navHtml": {
          "name": [
            "動作片",
            "喜劇片",
            "愛情片",
            "科幻片",
            "恐怖片",
            "劇情片",
            "戰爭片",
            "国产剧",
            "港台剧",
            "日韩剧",
            "欧美剧",
            "海外剧",
            "综艺",
            "纪录片"
          ],
          "cate": [
            "6",
            "7",
            "8",
            "9",
            "10",
            "11",
            "12",
            "13",
            "14",
            "15",
            "16",
            "27",
            "3",
            "28"
          ],
          "page": "1"
        },
        "html": {
          "episodes": {
            "hasUrlPrefix": false,
            "isListItemAttr": true,
            "listCss": "div.playlist_full",
            "isMultiList": true,
            "listCssMulti": "ul > li",
            "listItemAttr": "href",
            "listItemCss": "a",
            "listItemIndex": 0,
            "mainCss": "div.play_source",
            "mainIndex": 0
          },
          "nav": {
            "descAttr": "",
            "descCss": "em.voddate.voddate_year",
            "descIndex": 0,
            "hasUrlPrefix": false,
            "imgAttr": "data-original",
            "imgCss": "a",
            "imgIndex": 0,
            "isDescAttr": false,
            "isImgAttr": true,
            "isNameAttr": true,
            "isUrlAttr": true,
            "mainCss": "div.pannel.clearfix > ul",
            "mainListIndex": 0,
            "nameAttr": "title",
            "nameCss": "a",
            "nameIndex": 0,
            "searchListCss": "li",
            "urlAttr": "href",
            "urlCss": "a",
            "urlIndex": 0
          },
          "search": {
            "descAttr": "",
            "descCss": "span.pic_text.text_right",
            "descIndex": 0,
            "hasUrlPrefix": false,
            "imgAttr": "data-original",
            "imgCss": "a",
            "imgIndex": 0,
            "isDescAttr": false,
            "isImgAttr": true,
            "isNameAttr": true,
            "isUrlAttr": true,
            "mainCss": "div.pannel.search_box.clearfix",
            "mainListIndex": 0,
            "nameAttr": "title",
            "nameCss": "a",
            "nameIndex": 0,
            "searchListCss": "ul > li",
            "urlAttr": "href",
            "urlCss": "a",
            "urlIndex": 0
          }
        }
      }
    },
    {
      "name": "爱迪(规则)",
      "pic": "https://pkj99.github.io/demo/images/aidi.png",
      "type": "webPlug",
      "ads": "",
      "webUrl": "https://adys.tv/",
      "webOpen": false,
      "click": true,
      "webPlus": {
        "search_url": "https://adys.tv/vsearch/-------------.html?wd={kw}",
        "nav_url": "https://adys.tv/show/navCate--------navPage---.html",
        "web_name": "爱迪",
        "search": true,
        "navHtml": {
          "name": [
            "電影",
            "動作片",
            "喜劇片",
            "愛情片",
            "科幻片",
            "恐怖片",
            "劇情片",
            "戰爭片",
            "傳記",
            "連續劇",
            "大陸劇",
            "港台劇",
            "韓劇",
            "美劇",
            "日劇",
            "英劇",
            "泰劇",
            "其他劇",
            "綜藝",
            "內地綜藝",
            "港台綜藝",
            "韓國綜藝",
            "歐美綜藝",
            "動漫"
          ],
          "cate": [
            "dianying",
            "dongzuopian",
            "xijupian",
            "aiqingpian",
            "kehuanpian",
            "kongbupian",
            "juqingpian",
            "zhanzhengpian",
            "zhuanji",
            "lianxuju",
            "guochanju",
            "gangtaiju",
            "hanju",
            "meiju",
            "riju",
            "yingju",
            "taiju",
            "qita",
            "zongyi",
            "ndzy",
            "gtzy",
            "variety",
            "oumeizongyi",
            "dongman"
          ],
          "page": "1"
        },
        "cateHtml": {
          "isCate": false,
          "isYear": false,
          "isArea": false,
          "cate": "",
          "year": "",
          "area": ""
        },
        "html": {
          "episodes": {
            "hasUrlPrefix": true,
            "isListItemAttr": true,
            "listCss": "div.playlist_full",
            "isMultiList": true,
            "listCssMulti": "ul > li",
            "listItemAttr": "href",
            "listItemCss": "a",
            "listItemIndex": 0,
            "mainCss": "div.play_source",
            "mainIndex": 0
          },
          "nav": {
            "descAttr": "",
            "descCss": "span.pic_text.text_right",
            "descIndex": 0,
            "hasUrlPrefix": false,
            "imgAttr": "data-original",
            "imgCss": "a",
            "imgIndex": 0,
            "isDescAttr": false,
            "isImgAttr": true,
            "isNameAttr": false,
            "isUrlAttr": true,
            "mainCss": "ul.vodlist.vodlist_wi",
            "mainListIndex": 0,
            "nameAttr": "title",
            "nameCss": "a",
            "nameIndex": 1,
            "searchListCss": "li",
            "urlAttr": "href",
            "urlCss": "a",
            "urlIndex": 0
          },
          "search": {
            "descAttr": "",
            "descCss": "span.pic_text.text_right",
            "descIndex": 0,
            "hasUrlPrefix": false,
            "imgAttr": "data-original",
            "imgCss": "a",
            "imgIndex": 0,
            "isDescAttr": false,
            "isImgAttr": true,
            "isNameAttr": true,
            "isUrlAttr": true,
            "mainCss": "ul.vodlist.clearfix",
            "mainListIndex": 0,
            "nameAttr": "title",
            "nameCss": "a",
            "nameIndex": 0,
            "searchListCss": "li",
            "urlAttr": "href",
            "urlCss": "a",
            "urlIndex": 0
          }
        }
      }
    },
    {
      "name": "多腦(规则)",
      "pic": "https://pkj99.github.io/demo/images/duona.png",
      "type": "webPlug",
      "ads": "",
      "webUrl": "https://www.duonaovod.com",
      "webOpen": false,
      "click": true,
      "webPlus": {
        "search_url": "https://www.duonaovod.com/index.php/vod/search.html?wd={kw}",
        "nav_url": "https://www.duonaovod.com/index.php/vod/show/id/navCate/page/navPage.html",
        "web_name": "多腦",
        "search": true,
        "navHtml": {
          "name": [
            "電影",
            "動作片",
            "喜劇片",
            "愛情片",
            "科幻片",
            "恐怖片",
            "劇情片",
            "戰爭片",
            "連續劇",
            "大陸劇",
            "港台劇",
            "日韓劇",
            "歐美劇",
            "海外劇",
            "紀錄片",
            "綜藝",
            "內地港台綜藝",
            "日韓綜藝",
            "歐美綜藝",
            "動漫"
          ],
          "cate": [
            "1",
            "6",
            "7",
            "8",
            "9",
            "10",
            "11",
            "12",
            "2",
            "13",
            "14",
            "15",
            "16",
            "31",
            "20",
            "3",
            "27",
            "28",
            "29",
            "4"
          ],
          "page": "1"
        },
        "html": {
          "episodes": {
            "hasUrlPrefix": false,
            "isListItemAttr": true,
            "listCss": "div.playlist_full",
            "isMultiList": true,
            "listCssMulti": "ul > li",
            "listItemAttr": "href",
            "listItemCss": "a",
            "listItemIndex": 0,
            "mainCss": "div.play_source",
            "mainIndex": 0
          },
          "nav": {
            "descAttr": "",
            "descCss": "span.pic_text.text_right.text_dy",
            "descIndex": 0,
            "hasUrlPrefix": false,
            "imgAttr": "data-original",
            "imgCss": "a",
            "imgIndex": 0,
            "isDescAttr": false,
            "isImgAttr": true,
            "isNameAttr": true,
            "isUrlAttr": true,
            "mainCss": "ul.vodlist.vodlist_wi",
            "mainListIndex": 0,
            "nameAttr": "title",
            "nameCss": "a",
            "nameIndex": 1,
            "searchListCss": "li",
            "urlAttr": "href",
            "urlCss": "a",
            "urlIndex": 0
          },
          "search": {
            "descAttr": "",
            "descCss": "span.info_right",
            "descIndex": 0,
            "hasUrlPrefix": false,
            "imgAttr": "data-original",
            "imgCss": "a",
            "imgIndex": 0,
            "isDescAttr": false,
            "isImgAttr": true,
            "isNameAttr": true,
            "isUrlAttr": true,
            "mainCss": "ul.vodlist.clearfix",
            "mainListIndex": 0,
            "nameAttr": "title",
            "nameCss": "a",
            "nameIndex": 0,
            "searchListCss": "li",
            "urlAttr": "href",
            "urlCss": "a",
            "urlIndex": 0
          }
        }
      }
    },
    {
      "name": "唐人街(Web)",
      "pic": "https://pkj99.github.io/demo/images/watch_online.png",
      "keyDownPlay": false,
      "keyUpPlay": false,
      "userAgent": "PC",
      "ads": "",
      "webUrl": "https://www.tangrenjie.tv/",
      "webOpen": true,
      "click": true
    },
    {
      "name": "gimy(Web)",
      "pic": "https://pkj99.github.io/demo/images/watch_online.png",
      "keyDownPlay": false,
      "keyUpPlay": false,
      "userAgent": "PC",
      "ads": "",
      "webUrl": "https://gimy.ai/",
      "webOpen": true,
      "click": true
    },
    {
      "name": "nivod(Web)",
      "pic": "https://pkj99.github.io/demo/images/watch_online.png",
      "keyDownPlay": false,
      "keyUpPlay": false,
      "userAgent": "PC",
      "ads": "",
      "webUrl": "https://www.nivod.tv/class.html?channelId=1",
      "webOpen": true,
      "click": true
    },
    {
      "name": "haiwaikan(Web)",
      "pic": "https://www.tgcng.com/logo/3320150.jpg",
      "keyDownPlay": false,
      "keyUpPlay": false,
      "userAgent": "PC",
      "ads": "",
      "webUrl": "https://haiwaikan.com/index.php/vod/type/id/133.html",
      "webOpen": true,
      "click": true
    },
    {
      "name": "Radios.TW(Web)",
      "pic": "https://pkj99.github.io/demo/images/watch_online.png",
      "keyDownPlay": false,
      "keyUpPlay": false,
      "userAgent": "PC",
      "ads": "",
      "webUrl": "https://radios.tw/",
      "webOpen": true,
      "click": true
    }
  ]
}